{
  "appPageId" : "653c0261-e5ac-4a5c-930a-539967530b3c",
  "componentName" : "siteforce:sldsOneColLayout",
  "dataProviders" : [ ],
  "id" : "79f2d6d3-a28f-4ef8-919e-2715acdeb045",
  "label" : "Login",
  "regions" : [ {
    "components" : [ {
      "componentAttributes" : { },
      "componentName" : "salesforceIdentity:communityLogo2",
      "id" : "c726c1d3-c913-4b3c-8df2-b0ab13eb4742",
      "renderPriority" : "NEUTRAL",
      "renditionMap" : { },
      "type" : "component"
    }, {
      "componentAttributes" : {
        "forgotPasswordLabel" : "Forgot your password?",
        "forgotPasswordUrl" : "/ForgotPassword",
        "loginButtonLabel" : "Log in",
        "passwordLabel" : "Password",
        "selfRegisterLabel" : "Not a member?",
        "selfRegisterUrl" : "/SelfRegister",
        "startUrl" : "",
        "usernameLabel" : "Username"
      },
      "componentName" : "salesforceIdentity:loginForm2",
      "id" : "81f573b0-8674-4211-b0b2-1b172b210d00",
      "renderPriority" : "NEUTRAL",
      "renditionMap" : { },
      "type" : "component"
    }, {
      "componentAttributes" : {
        "headerText" : "",
        "showHeader" : false,
        "useCommunityDomainSso" : true
      },
      "componentName" : "salesforceIdentity:socialLogin2",
      "id" : "b34d54ba-d1ec-4b11-8be7-bc79e5bfc5bd",
      "renderPriority" : "NEUTRAL",
      "renditionMap" : { },
      "type" : "component"
    }, {
      "componentAttributes" : {
        "employeeLoginLinkLabel" : "Are you an employee? Login here"
      },
      "componentName" : "salesforceIdentity:employeeLoginLink2",
      "id" : "710a50d1-84e4-4109-b3cb-ff726fc9db36",
      "renderPriority" : "NEUTRAL",
      "renditionMap" : { },
      "type" : "component"
    } ],
    "id" : "e1c8fdc8-4aaf-4450-8807-2ba698784b47",
    "regionName" : "content",
    "type" : "region"
  }, {
    "components" : [ {
      "componentAttributes" : {
        "customHeadTags" : "",
        "description" : "",
        "title" : "Login"
      },
      "componentName" : "forceCommunity:seoAssistant",
      "id" : "063d4395-c3d0-4bdb-8e1b-399f0217c521",
      "renditionMap" : { },
      "type" : "component"
    } ],
    "id" : "5ea4fbcd-4009-470e-a593-85095c7b0e33",
    "regionName" : "sfdcHiddenRegion",
    "type" : "region"
  } ],
  "themeLayoutType" : "Login",
  "type" : "view",
  "viewType" : "login-home"
}